README.rst
setup.py
uz/__init__.py
uz/analysis.py
uz/cli.py
uz/util.py
uz.egg-info/PKG-INFO
uz.egg-info/SOURCES.txt
uz.egg-info/dependency_links.txt
uz.egg-info/entry_points.txt
uz.egg-info/requires.txt
uz.egg-info/top_level.txt