Metadata-Version: 1.0
Name: uz
Version: 0.2
Summary: uz extracts files of all sorts
Home-page: http://github.com/mbr/uz
Author: Marc Brinkmann
Author-email: git@marcbrinkmann.de
License: MIT
Platform: UNKNOWN
